{
    "event_id": "a_thing_of_the_past",
    "event_title": "A Thing of the Past",
    "url": "https://www.lessonsinlove.wiki/index.php?title=A_Thing_of_the_Past",
    "event_type": "Event",
    "primary_character": "Yuki Yamaguchi",
    "chapter": "Chapter 2",
    "interactivity": {
        "requirements": "None",
        "to_get_this_event": "Autoplay after Opposite Directions",
        "to_miss_this_event": "This event is not missable.",
        "choices": [],
        "effects": []
    },
    "progression": {
        "locations": [
            "Unspecified Convenience Store"
        ],
        "synopsis": "As thanks for helping pass out fliers, Yuki takes Sensei to a nearby convenience store and offers to buy him some food. The two discuss Sensei's inexplicable ability to attract teenage girls, and Yuki's lack of romantic experience. Just as the two start to flirt, Yumi walks in and quickly flies into a fury seeing her mother act so familiar with Sensei.",
        "participating_characters": [
            "Sensei",
            "Yuki Yamaguchi",
            "Yumi Yamaguchi"
        ],
        "trivia": []
    },
    "technical_information": {
        "event_references": {
            "event_default_name": "A Thing of the Past",
            "event_script_names": "yukidate10p2",
            "event_missed_name": "This event is not missable."
        },
        "backgrounds": [
            "yukiconvenience"
        ],
        "music_tracks": [
            "recovery.mp3",
            "undersea.mp3"
        ],
        "changelog": [
            "This Event was added in Update .21p2."
        ]
    },
    "navigation": {
        "previous_event": "Opposite Directions",
        "next_event": "Funeral Plans"
    }
}